bda.intellidatetime-1.4-nspkg.pth
bda/intellidatetime/__init__.py
bda/intellidatetime/configure.zcml
bda/intellidatetime/converter.py
bda/intellidatetime/interfaces.py
bda/intellidatetime/tests.py
bda.intellidatetime-1.4.dist-info/LICENSE.rst
bda.intellidatetime-1.4.dist-info/METADATA
bda.intellidatetime-1.4.dist-info/WHEEL
bda.intellidatetime-1.4.dist-info/namespace_packages.txt
bda.intellidatetime-1.4.dist-info/top_level.txt
bda.intellidatetime-1.4.dist-info/RECORD
