Metadata-Version: 2.1
Name: bda.intellidatetime
Version: 1.4
Summary: bda.intellidatetime
Home-page: https://github.com/bluedynamics/bda.intellidatetime
Author: BlueDynamics Alliance
Author-email: dev@bluedynamics.com
License: Simplified BSD
Platform: UNKNOWN
Classifier: Development Status :: 5 - Production/Stable
Classifier: Operating System :: OS Independent
Classifier: Programming Language :: Python
Classifier: Topic :: Utilities
Requires-Dist: setuptools
Requires-Dist: zope.interface
